src/__init__.py
src/cloudwatch_metrics.py
src/data_utils.py
src/decorators.py
src/distributed_property.py
src/dynamo_data_utils.py
src/dynamo_helper.py
src/dynamo_streams.py
src/dynamo_utils.py
src/environments.py
src/event_bus.py
src/flask_utilities.py
src/geography_helpers.py
src/google_geocode_client.py
src/helper_utils.py
src/kinesis_helper.py
src/lambda_utils.py
src/offer_utils.py
src/offers_from_property.py
src/properly_logging.py
src/property_remapping.py
src/redshift_helper.py
src/schemas.py
src/secrets_manager.py
src/sqs_utils.py
src/table_helper.py
src/user_auth.py
properly_util_python-0.32.0.dist-info/METADATA
properly_util_python-0.32.0.dist-info/WHEEL
properly_util_python-0.32.0.dist-info/top_level.txt
properly_util_python-0.32.0.dist-info/RECORD
