Metadata-Version: 2.1
Name: properly-util-python
Version: 0.32.0
Summary: Utility and helper functions for common Properly operations in python.
Home-page: https://github.com/GoProperly/properly-util-python
Author: GoProperly
Author-email: info@goproperly.com
Classifier: Programming Language :: Python :: 3
Requires-Dist: orjson (<3.6.9,>3)
Requires-Dist: deprecation (==2.1.0)
